earhorn/__init__.py
earhorn/event.py
earhorn/main.py
earhorn/prometheus.py
earhorn/stats.py
earhorn/stream.py
earhorn/stream_archive.py
earhorn/stream_archive_s3.py
earhorn/stream_silence.py
earhorn-0.21.1.dist-info/licenses/LICENSE
earhorn-0.21.1.dist-info/METADATA
earhorn-0.21.1.dist-info/WHEEL
earhorn-0.21.1.dist-info/entry_points.txt
earhorn-0.21.1.dist-info/top_level.txt
earhorn-0.21.1.dist-info/RECORD
