Metadata-Version: 2.4
Name: earhorn
Version: 0.21.1
Summary: Listen, monitor and archive your streams!
Author-email: Joola <jooola@users.noreply.github.com>
License-Expression: GPL-3.0-only
Classifier: Development Status :: 3 - Alpha
Classifier: Environment :: Console
Classifier: Programming Language :: Python
Classifier: Programming Language :: Python :: 3
Classifier: Programming Language :: Python :: 3.9
Classifier: Programming Language :: Python :: 3.10
Classifier: Programming Language :: Python :: 3.11
Classifier: Programming Language :: Python :: 3.12
Classifier: Programming Language :: Python :: 3.13
Requires-Python: >=3.9
License-File: LICENSE
Requires-Dist: click<9.0,>=8.0.1
Requires-Dist: httpx<0.29,>=0.28.0
Requires-Dist: lxml<6.1,>=6
Requires-Dist: prometheus-client<0.23,>=0.22.1
Requires-Dist: pydantic<3.0,>=2.10.6
Requires-Dist: python-dotenv<2.0,>=1.0.0
Requires-Dist: typing-extensions>=4.2.0
Provides-Extra: dev
Requires-Dist: lxml-stubs<0.6,>=0.5.0; extra == "dev"
Requires-Dist: moto<6.0,>=5.0.0; extra == "dev"
Requires-Dist: mypy<2.0,>=1.0; extra == "dev"
Requires-Dist: pylint<4.0,>=3.0.0; extra == "dev"
Requires-Dist: pytest-cov<7.1,>=7; extra == "dev"
Requires-Dist: pytest-httpx<0.36,>=0.35.0; extra == "dev"
Requires-Dist: pytest-xdist<4.0,>=3.0.0; extra == "dev"
Requires-Dist: pytest<9.0,>=8.0.0; extra == "dev"
Requires-Dist: testcontainers<5.0,>=4.0.0; extra == "dev"
Requires-Dist: types-boto3<2.0,>=1.0.2; extra == "dev"
Provides-Extra: s3
Requires-Dist: boto3<2.0,>=1.24.8; extra == "s3"
Provides-Extra: sentry
Requires-Dist: sentry-sdk<2.38,>=2.37; extra == "sentry"
Dynamic: license-file
